helix/third_party/VERSION.py
helix/third_party/__init__.py
helix/third_party/bcftools.exe
helix/third_party/bgzip.exe
helix/third_party/bwa.exe
helix/third_party/gzip.exe
helix/third_party/htsfile.exe
helix/third_party/minimap2.exe
helix/third_party/msys-2.0.dll
helix/third_party/msys-bz2-1.dll
helix/third_party/msys-lzma-5.dll
helix/third_party/msys-ncursesw6.dll
helix/third_party/msys-z.dll
helix/third_party/samtools.exe
helix/third_party/tabix.exe
doublehelix_external-0.0.2.dist-info/METADATA
doublehelix_external-0.0.2.dist-info/WHEEL
doublehelix_external-0.0.2.dist-info/top_level.txt
doublehelix_external-0.0.2.dist-info/RECORD
