Metadata-Version: 2.1
Name: doublehelix-external
Version: 0.0.2
Summary: Genomic data manipulation tool
Author-email: chaplin89 <unavailable@doublehelix.com>
Project-URL: homepage, https://github.com/DoubleHelixApp/External
Project-URL: Repository, https://github.com/DoubleHelixApp/External
Project-URL: Documentation, https://doublehelixapp.github.io
Project-URL: Issues, https://github.com/DoubleHelixApp/External/issues
Project-URL: Changelog, https://github.com/DoubleHelixApp/External/releases
Keywords: bioinformatics
Classifier: Development Status :: 1 - Planning
Classifier: Intended Audience :: Developers
Classifier: Intended Audience :: Science/Research
Classifier: License :: OSI Approved :: BSD License
Classifier: License :: OSI Approved :: MIT License
Classifier: Operating System :: OS Independent
Classifier: Programming Language :: Python :: 3.12
Classifier: Topic :: Scientific/Engineering :: Bio-Informatics
